langchain_cohere/__init__.py
langchain_cohere/chains/summarize/__init__.py
langchain_cohere/chains/summarize/prompt.py
langchain_cohere/chains/summarize/summarize_chain.py
langchain_cohere/chat_models.py
langchain_cohere/cohere_agent.py
langchain_cohere/common.py
langchain_cohere/embeddings.py
langchain_cohere/llms.py
langchain_cohere/py.typed
langchain_cohere/rag_retrievers.py
langchain_cohere/react_multi_hop/__init__.py
langchain_cohere/react_multi_hop/agent.py
langchain_cohere/react_multi_hop/default_prompt_constants.py
langchain_cohere/react_multi_hop/parsing.py
langchain_cohere/react_multi_hop/prompt.py
langchain_cohere/rerank.py
langchain_cohere/sql_agent/agent.py
langchain_cohere/sql_agent/prompts.py
langchain_cohere/utils.py
langchain_cohere-0.4.1.dist-info/LICENSE
langchain_cohere-0.4.1.dist-info/METADATA
langchain_cohere-0.4.1.dist-info/WHEEL
langchain_cohere-0.4.1.dist-info/RECORD
